[
  {
    "id": 1,
    "eventId": 1,
    "gameCharacterUnitId": 1,
    "cardAttr": "mysterious",
    "bonusRate": 50
  },
  {
    "id": 2,
    "eventId": 1,
    "gameCharacterUnitId": 2,
    "cardAttr": "mysterious",
    "bonusRate": 50
  },
  {
    "id": 3,
    "eventId": 1,
    "gameCharacterUnitId": 3,
    "cardAttr": "mysterious",
    "bonusRate": 50
  },
  {
    "id": 4,
    "eventId": 1,
    "gameCharacterUnitId": 4,
    "cardAttr": "mysterious",
    "bonusRate": 50
  },
  {
    "id": 5,
    "eventId": 1,
    "gameCharacterUnitId": 42,
    "cardAttr": "mysterious",
    "bonusRate": 50
  },
  {
    "id": 6,
    "eventId": 1,
    "gameCharacterUnitId": 1,
    "bonusRate": 20
  },
  {
    "id": 7,
    "eventId": 1,
    "gameCharacterUnitId": 2,
    "bonusRate": 20
  },
  {
    "id": 8,
    "eventId": 1,
    "gameCharacterUnitId": 3,
    "bonusRate": 20
  },
  {
    "id": 9,
    "eventId": 1,
    "gameCharacterUnitId": 4,
    "bonusRate": 20
  },
  {
    "id": 10,
    "eventId": 1,
    "gameCharacterUnitId": 42,
    "bonusRate": 20
  },
  {
    "id": 11,
    "eventId": 1,
    "cardAttr": "mysterious",
    "bonusRate": 20
  },
  {
    "id": 12,
    "eventId": 2,
    "gameCharacterUnitId": 17,
    "cardAttr": "cool",
    "bonusRate": 50
  },
  {
    "id": 13,
    "eventId": 2,
    "gameCharacterUnitId": 18,
    "cardAttr": "cool",
    "bonusRate": 50
  },
  {
    "id": 14,
    "eventId": 2,
    "gameCharacterUnitId": 19,
    "cardAttr": "cool",
    "bonusRate": 50
  },
  {
    "id": 15,
    "eventId": 2,
    "gameCharacterUnitId": 20,
    "cardAttr": "cool",
    "bonusRate": 50
  },
  {
    "id": 16,
    "eventId": 2,
    "gameCharacterUnitId": 31,
    "cardAttr": "cool",
    "bonusRate": 50
  },
  {
    "id": 17,
    "eventId": 2,
    "gameCharacterUnitId": 17,
    "bonusRate": 20
  },
  {
    "id": 18,
    "eventId": 2,
    "gameCharacterUnitId": 18,
    "bonusRate": 20
  },
  {
    "id": 19,
    "eventId": 2,
    "gameCharacterUnitId": 19,
    "bonusRate": 20
  },
  {
    "id": 20,
    "eventId": 2,
    "gameCharacterUnitId": 20,
    "bonusRate": 20
  },
  {
    "id": 21,
    "eventId": 2,
    "gameCharacterUnitId": 31,
    "bonusRate": 20
  },
  {
    "id": 22,
    "eventId": 2,
    "cardAttr": "cool",
    "bonusRate": 20
  }
]