[
  {
    "id": 1,
    "honorType": "character",
    "name": "一歌ファン"
  },
  {
    "id": 2,
    "honorType": "character",
    "name": "咲希ファン"
  },
  {
    "id": 3,
    "honorType": "character",
    "name": "穂波ファン"
  },
  {
    "id": 4,
    "honorType": "character",
    "name": "志歩ファン"
  },
  {
    "id": 5,
    "honorType": "character",
    "name": "みのりファン"
  },
  {
    "id": 6,
    "honorType": "character",
    "name": "遥ファン"
  },
  {
    "id": 7,
    "honorType": "character",
    "name": "愛莉ファン"
  },
  {
    "id": 8,
    "honorType": "character",
    "name": "雫ファン"
  },
  {
    "id": 9,
    "honorType": "character",
    "name": "こはねファン"
  },
  {
    "id": 10,
    "honorType": "character",
    "name": "杏ファン"
  },
  {
    "id": 11,
    "honorType": "character",
    "name": "彰人ファン"
  },
  {
    "id": 12,
    "honorType": "character",
    "name": "冬弥ファン"
  },
  {
    "id": 13,
    "honorType": "character",
    "name": "司ファン"
  },
  {
    "id": 14,
    "honorType": "character",
    "name": "えむファン"
  },
  {
    "id": 15,
    "honorType": "character",
    "name": "寧々ファン"
  },
  {
    "id": 16,
    "honorType": "character",
    "name": "類ファン"
  },
  {
    "id": 17,
    "honorType": "character",
    "name": "奏ファン"
  },
  {
    "id": 18,
    "honorType": "character",
    "name": "まふゆファン"
  },
  {
    "id": 19,
    "honorType": "character",
    "name": "絵名ファン"
  },
  {
    "id": 20,
    "honorType": "character",
    "name": "瑞希ファン"
  },
  {
    "id": 21,
    "honorType": "character",
    "name": "ミクファン"
  },
  {
    "id": 22,
    "honorType": "character",
    "name": "リンファン"
  },
  {
    "id": 23,
    "honorType": "character",
    "name": "レンファン"
  },
  {
    "id": 24,
    "honorType": "character",
    "name": "ルカファン"
  },
  {
    "id": 25,
    "honorType": "character",
    "name": "MEIKOファン"
  },
  {
    "id": 26,
    "honorType": "character",
    "name": "KAITOファン"
  },
  {
    "id": 27,
    "honorType": "achievement",
    "name": "39！"
  },
  {
    "id": 28,
    "honorType": "achievement",
    "name": "3939！"
  },
  {
    "id": 29,
    "honorType": "achievement",
    "name": "一人前"
  },
  {
    "id": 30,
    "honorType": "achievement",
    "name": "ベテラン"
  },
  {
    "id": 31,
    "honorType": "achievement",
    "name": "皆勤賞"
  },
  {
    "id": 32,
    "honorType": "achievement",
    "name": "昔からいる"
  },
  {
    "id": 33,
    "honorType": "achievement",
    "name": "もうひとつの歌声"
  },
  {
    "id": 34,
    "honorType": "achievement",
    "name": "箱推し"
  },
  {
    "id": 35,
    "honorType": "achievement",
    "name": "アイテムマイスター"
  },
  {
    "id": 36,
    "honorType": "achievement",
    "name": "みんな大好き"
  },
  {
    "id": 37,
    "honorType": "achievement",
    "name": "完璧主義"
  },
  {
    "id": 38,
    "honorType": "achievement",
    "name": "皆伝"
  },
  {
    "id": 39,
    "honorType": "achievement",
    "name": "真・皆伝"
  },
  {
    "id": 40,
    "honorType": "achievement",
    "name": "安全第一"
  },
  {
    "id": 41,
    "honorType": "achievement",
    "name": "ネバーギブアップ"
  },
  {
    "id": 42,
    "honorType": "achievement",
    "name": "腱鞘炎"
  },
  {
    "id": 43,
    "honorType": "achievement",
    "name": "ミリオネア"
  },
  {
    "id": 44,
    "honorType": "achievement",
    "name": "みんなでフルコンボ！"
  },
  {
    "id": 45,
    "honorType": "achievement",
    "name": "シンクロニシティ"
  },
  {
    "id": 46,
    "honorType": "achievement",
    "name": "ドッペルゲンガー"
  },
  {
    "id": 47,
    "honorType": "achievement",
    "name": "あいさつが大事"
  },
  {
    "id": 49,
    "honorType": "achievement",
    "name": "出会いと別れ"
  },
  {
    "id": 50,
    "honorType": "achievement",
    "name": "スタンプコレクター"
  },
  {
    "id": 51,
    "honorType": "achievement",
    "name": "なんでも知ってる"
  },
  {
    "id": 52,
    "honorType": "achievement",
    "name": "ちゃんと読んでる"
  },
  {
    "id": 53,
    "honorType": "achievement",
    "name": "高校1年生"
  },
  {
    "id": 54,
    "honorType": "achievement",
    "name": "高校2年生"
  },
  {
    "id": 55,
    "honorType": "achievement",
    "name": "宮女生徒"
  },
  {
    "id": 56,
    "honorType": "achievement",
    "name": "神山生徒"
  },
  {
    "id": 57,
    "honorType": "achievement",
    "name": "ボーイズマスター"
  },
  {
    "id": 58,
    "honorType": "achievement",
    "name": "MVP"
  },
  {
    "id": 59,
    "honorType": "achievement",
    "name": "SUPER STAR"
  },
  {
    "id": 60,
    "honorType": "achievement",
    "name": "ファッションリーダー"
  },
  {
    "id": 71,
    "honorType": "event",
    "name": "雨上がりの一番星"
  },
  {
    "id": 72,
    "honorType": "achievement",
    "name": "レオニ応援隊"
  },
  {
    "id": 73,
    "honorType": "achievement",
    "name": "モモジャン応援隊"
  },
  {
    "id": 74,
    "honorType": "achievement",
    "name": "ビビバス応援隊"
  },
  {
    "id": 75,
    "honorType": "achievement",
    "name": "ワンダショ応援隊"
  },
  {
    "id": 76,
    "honorType": "achievement",
    "name": "ニーゴ応援隊"
  },
  {
    "id": 77,
    "honorType": "achievement",
    "name": "バーチャル・シンガー応援隊"
  },
  {
    "id": 80,
    "honorType": "event",
    "name": "HAPPY BIRTHDAY 穂波 2020.10.27"
  },
  {
    "id": 81,
    "honorType": "event",
    "name": "HAPPY BIRTHDAY 志歩 2021.1.8"
  },
  {
    "id": 82,
    "honorType": "event",
    "name": "HAPPY BIRTHDAY みのり 2021.4.14"
  },
  {
    "id": 83,
    "honorType": "event",
    "name": "HAPPY BIRTHDAY 遥 2020.10.5"
  },
  {
    "id": 84,
    "honorType": "event",
    "name": "HAPPY BIRTHDAY 愛莉 2021.3.19"
  },
  {
    "id": 85,
    "honorType": "event",
    "name": "HAPPY BIRTHDAY 雫 2020.12.6"
  },
  {
    "id": 86,
    "honorType": "event",
    "name": "HAPPY BIRTHDAY こはね 2021.3.2"
  },
  {
    "id": 88,
    "honorType": "event",
    "name": "HAPPY BIRTHDAY 彰人 2020.11.12"
  },
  {
    "id": 94,
    "honorType": "event",
    "name": "HAPPY BIRTHDAY 奏 2021.2.10"
  },
  {
    "id": 95,
    "honorType": "event",
    "name": "HAPPY BIRTHDAY まふゆ 2021.1.27"
  },
  {
    "id": 99,
    "honorType": "event",
    "name": "HAPPY ANNIVERSARY リン 2020.12.27"
  },
  {
    "id": 100,
    "honorType": "event",
    "name": "HAPPY ANNIVERSARY レン 2020.12.27"
  },
  {
    "id": 101,
    "honorType": "event",
    "name": "HAPPY ANNIVERSARY ルカ 2021.1.30"
  },
  {
    "id": 102,
    "honorType": "event",
    "name": "HAPPY ANNIVERSARY MEIKO 2020.11.5"
  },
  {
    "id": 103,
    "honorType": "event",
    "name": "HAPPY ANNIVERSARY KAITO 2021.2.17"
  },
  {
    "id": 104,
    "honorType": "event",
    "name": "囚われのマリオネット"
  },
  {
    "id": 105,
    "honorType": "event",
    "name": "全力！ワンダーハロウィン！"
  },
  {
    "id": 106,
    "honorType": "event",
    "name": "ハロウィン2020"
  },
  {
    "id": 107,
    "honorType": "event",
    "name": "走れ！体育祭！～実行委員は大忙し～"
  },
  {
    "id": 108,
    "honorType": "event",
    "name": "ここからRE:START！"
  },
  {
    "id": 110,
    "honorType": "achievement",
    "name": "プラチナ"
  },
  {
    "id": 111,
    "honorType": "event",
    "name": "いつか、背中あわせのリリックを"
  },
  {
    "id": 112,
    "honorType": "event",
    "name": "KAMIKOU FESTIVAL！"
  },
  {
    "id": 113,
    "honorType": "event",
    "name": "聖なる夜に、この歌声を"
  },
  {
    "id": 114,
    "honorType": "event",
    "name": "クリスマス2020"
  },
  {
    "id": 115,
    "honorType": "event",
    "name": "RAGE プロジェクトセカイ 2020 Winter powered by AQUOS"
  },
  {
    "id": 116,
    "honorType": "event",
    "name": "2021カウントダウンライブ"
  },
  {
    "id": 117,
    "honorType": "event",
    "name": "セカイのハッピーニューイヤー！"
  },
  {
    "id": 118,
    "honorType": "event",
    "name": "揺れるまま、でも君は前へ"
  },
  {
    "id": 119,
    "honorType": "event",
    "name": "Color of Myself！"
  },
  {
    "id": 120,
    "honorType": "event",
    "name": "Period of NOCTURNE"
  },
  {
    "id": 121,
    "honorType": "achievement",
    "name": "フレンド募集中"
  },
  {
    "id": 122,
    "honorType": "achievement",
    "name": "友達100人できるかな"
  },
  {
    "id": 123,
    "honorType": "achievement",
    "name": "ベストフレンド"
  },
  {
    "id": 124,
    "honorType": "event",
    "name": "バレンタイン2021"
  },
  {
    "id": 125,
    "honorType": "event",
    "name": "響くトワイライトパレード"
  },
  {
    "id": 126,
    "honorType": "event",
    "name": "満たされないペイルカラー"
  },
  {
    "id": 127,
    "honorType": "event",
    "name": "スマイルオブドリーマー"
  },
  {
    "id": 128,
    "honorType": "event",
    "name": "ホワイトデー2021"
  },
  {
    "id": 129,
    "honorType": "event",
    "name": "天馬さんちのひな祭り"
  },
  {
    "id": 130,
    "honorType": "event",
    "name": "届け！HOPEFUL STAGE♪"
  },
  {
    "id": 131,
    "honorType": "event",
    "name": "君と歌う、桜舞う世界で"
  },
  {
    "id": 132,
    "honorType": "event",
    "name": "シークレット・ディスタンス"
  },
  {
    "id": 134,
    "honorType": "achievement",
    "name": "ダイヤモンド"
  }
]