[
  {
    "homeBannerId": 1289,
    "seq": 90,
    "homeBannerType": "general",
    "name": "[ガチャ]ハピネスパッケージガチャ",
    "assetbundleName": "banner_gacha745",
    "transitionDestinationType": "gacha",
    "transitionDestinationId": 745,
    "startAt": 1748228400000,
    "endAt": 1749005999000
  },
  {
    "homeBannerId": 1291,
    "seq": 110,
    "homeBannerType": "general",
    "name": "[ガチャ]ビビバス箱イベ_ガチャバナー",
    "assetbundleName": "banner_gacha746",
    "transitionDestinationType": "gacha",
    "transitionDestinationId": 746,
    "startAt": 1748660400000,
    "endAt": 1749438000000
  },
  {
    "homeBannerId": 1293,
    "seq": 100,
    "homeBannerType": "event",
    "name": "[イベント]ビビバス箱イベ_イベントバナー",
    "assetbundleName": "event_higher_2025",
    "transitionDestinationType": "event",
    "transitionDestinationId": 169,
    "startAt": 1748671200000,
    "endAt": 1749466800000
  },
  {
    "homeBannerId": 1296,
    "seq": 130,
    "homeBannerType": "general",
    "name": "[25時、ナイトコードで。]ワールドリンクイベントサポートガチャ",
    "assetbundleName": "banner_gacha747",
    "transitionDestinationType": "gacha",
    "transitionDestinationId": 747,
    "startAt": 1748833200000,
    "endAt": 1750647600000
  }
]